trytond/modules/calendar/__init__.py
trytond/modules/calendar/caldav.py
trytond/modules/calendar/calendar.xml
trytond/modules/calendar/calendar_.py
trytond/modules/calendar/res.py
trytond/modules/calendar/tryton.cfg
trytond/modules/calendar/webdav.py
trytond/modules/calendar/locale/bg.po
trytond/modules/calendar/locale/ca.po
trytond/modules/calendar/locale/cs.po
trytond/modules/calendar/locale/de.po
trytond/modules/calendar/locale/es.po
trytond/modules/calendar/locale/es_419.po
trytond/modules/calendar/locale/fr.po
trytond/modules/calendar/locale/hu_HU.po
trytond/modules/calendar/locale/it_IT.po
trytond/modules/calendar/locale/ja_JP.po
trytond/modules/calendar/locale/lo.po
trytond/modules/calendar/locale/lt.po
trytond/modules/calendar/locale/nl.po
trytond/modules/calendar/locale/pl.po
trytond/modules/calendar/locale/pt_BR.po
trytond/modules/calendar/locale/ru.po
trytond/modules/calendar/locale/sl.po
trytond/modules/calendar/locale/zh_CN.po
trytond/modules/calendar/tests/__init__.py
trytond/modules/calendar/tests/scenario_calendar.py
trytond/modules/calendar/tests/test_calendar.py
trytond/modules/calendar/view/attendee_form.xml
trytond/modules/calendar/view/attendee_tree.xml
trytond/modules/calendar/view/calendar_form.xml
trytond/modules/calendar/view/calendar_tree.xml
trytond/modules/calendar/view/category_form.xml
trytond/modules/calendar/view/category_tree.xml
trytond/modules/calendar/view/event_form.xml
trytond/modules/calendar/view/event_tree.xml
trytond/modules/calendar/view/event_tree_occurence.xml
trytond/modules/calendar/view/exdate_form.xml
trytond/modules/calendar/view/exdate_tree.xml
trytond/modules/calendar/view/exrule_form.xml
trytond/modules/calendar/view/exrule_tree.xml
trytond/modules/calendar/view/location_form.xml
trytond/modules/calendar/view/location_tree.xml
trytond/modules/calendar/view/rdate_form.xml
trytond/modules/calendar/view/rdate_tree.xml
trytond/modules/calendar/view/rrule_form.xml
trytond_calendar-4.2.0.dist-info/DESCRIPTION.rst
trytond_calendar-4.2.0.dist-info/METADATA
trytond_calendar-4.2.0.dist-info/RECORD
trytond_calendar-4.2.0.dist-info/WHEEL
trytond_calendar-4.2.0.dist-info/entry_points.txt
trytond_calendar-4.2.0.dist-info/metadata.json
trytond_calendar-4.2.0.dist-info/top_level.txt
